pythonvba/__init__.py
pythonvba/pythonvba.py
pythonvba-0.0.1.dist-info/METADATA
pythonvba-0.0.1.dist-info/WHEEL
pythonvba-0.0.1.dist-info/top_level.txt
pythonvba-0.0.1.dist-info/RECORD
