Metadata-Version: 2.1
Name: pythonvba
Version: 0.0.1
Summary: Run Python on VBA
Home-page: https://pythonvba.com
Author: Christoph Chester Cury
Author-email: Christoph Cury <cury.grupos@gmail.com>
Project-URL: Homepage, https://pythonvba.com
Project-URL: Bug Tracker, https://github.com/
Classifier: Programming Language :: Python :: 3
Classifier: License :: OSI Approved :: MIT License
Classifier: Operating System :: OS Independent
Requires-Python: >=3.7
